gisinfo_c/__init__.py
gisinfo_c/geo_info.cp36-win_amd64.pyd
gisinfo_c/tool/__init__.py
gisinfo_c/tool/geoinfo_tool.cp36-win_amd64.pyd
gisinfo_c/tool/raster_tool.cp36-win_amd64.pyd
gisinfo_c/tool/vector_tool.cp36-win_amd64.pyd
gisinfo_c-0.0.5.dist-info/METADATA
gisinfo_c-0.0.5.dist-info/WHEEL
gisinfo_c-0.0.5.dist-info/top_level.txt
gisinfo_c-0.0.5.dist-info/RECORD
