Metadata-Version: 2.1
Name: gisinfo-c
Version: 0.0.5
Summary: Short Time Fourier Transform
Home-page: UNKNOWN
Author: yzy
Author-email: yangzy@datall.cn
License: UNKNOWN
Platform: UNKNOWN
Requires: numpy
